superduper_anthropic/__init__.py
superduper_anthropic/model.py
superduper_anthropic-0.10.0.dist-info/licenses/LICENSE
superduper_anthropic-0.10.0.dist-info/METADATA
superduper_anthropic-0.10.0.dist-info/WHEEL
superduper_anthropic-0.10.0.dist-info/top_level.txt
superduper_anthropic-0.10.0.dist-info/RECORD
